cli/__init__.py
cli/prompts/midjourney.txt
cli/prompts/suno.txt
cli/prompts/udio.txt
cli/src/__init__.py
cli/src/agents_config.py
cli/src/cli.py
cli/src/history.py
cli/src/prompt_composer.py
cli/src/tokenization.py
cli/src/tracing.py
cli/src/tracing_config.py
cli/src/utils.py
prompt_surfer-0.1.7.dist-info/licenses/LICENSE
prompt_surfer-0.1.7.dist-info/METADATA
prompt_surfer-0.1.7.dist-info/WHEEL
prompt_surfer-0.1.7.dist-info/entry_points.txt
prompt_surfer-0.1.7.dist-info/top_level.txt
prompt_surfer-0.1.7.dist-info/RECORD
