Metadata-Version: 2.4
Name: prompt-surfer
Version: 0.1.7
Summary: A retro-styled terminal application for generating AI prompts across multiple creative platforms
Home-page: https://github.com/jadentripp/prompt-surfer
Author: Jaden Tripp
Author-email: Jaden Tripp <jadenitripp@gmail.com>
License: MIT
Project-URL: Homepage, https://github.com/jadentripp/prompt-surfer
Project-URL: Bug Tracker, https://github.com/jadentripp/prompt-surfer/issues
Keywords: ai,prompt,midjourney,suno,udio,openai,cli,terminal,tui
Classifier: Programming Language :: Python :: 3
Classifier: Programming Language :: Python :: 3.8
Classifier: Programming Language :: Python :: 3.9
Classifier: Programming Language :: Python :: 3.10
Classifier: Programming Language :: Python :: 3.11
Classifier: Operating System :: OS Independent
Classifier: Environment :: Console
Classifier: Topic :: Utilities
Classifier: Topic :: Artistic Software
Classifier: Topic :: Text Processing :: Markup
Requires-Python: >=3.8
License-File: LICENSE
Requires-Dist: openai>=1.3.0
Requires-Dist: openai-agents>=0.0.11
Requires-Dist: python-dotenv>=1.0.0
Requires-Dist: rich>=13.7.0
Requires-Dist: questionary>=2.0.0
Requires-Dist: tiktoken>=0.5.1
Requires-Dist: pyperclip>=1.8.2
Requires-Dist: aiohttp>=3.9.1
Requires-Dist: asyncio>=3.4.3
Dynamic: author
Dynamic: home-page
Dynamic: license-file
Dynamic: requires-python
